.coveragerc
.testr.conf
.travis.yml
AUTHORS
CHANGELOG.md
ChangeLog
LICENSE
MANIFEST.in
README.md
babel.cfg
requirements.txt
run.cmd
run.sh
setup.cfg
setup.py
test-requirements.txt
tox.ini
window-dev.md
doc/source/conf.py
doc/source/index.rst
oneview_redfish_toolkit/__init__.py
oneview_redfish_toolkit/all_subscription.json
oneview_redfish_toolkit/app.py
oneview_redfish_toolkit/category_resource.py
oneview_redfish_toolkit/client_session.py
oneview_redfish_toolkit/config.py
oneview_redfish_toolkit/connection.py
oneview_redfish_toolkit/event_dispatcher.py
oneview_redfish_toolkit/handler_multiple_oneview.py
oneview_redfish_toolkit/multiple_oneview.py
oneview_redfish_toolkit/single_oneview_context.py
oneview_redfish_toolkit/strategy_multiple_oneview.py
oneview_redfish_toolkit/util.py
oneview_redfish_toolkit.egg-info/PKG-INFO
oneview_redfish_toolkit.egg-info/SOURCES.txt
oneview_redfish_toolkit.egg-info/dependency_links.txt
oneview_redfish_toolkit.egg-info/not-zip-safe
oneview_redfish_toolkit.egg-info/pbr.json
oneview_redfish_toolkit.egg-info/requires.txt
oneview_redfish_toolkit.egg-info/top_level.txt
oneview_redfish_toolkit/api/__init__.py
oneview_redfish_toolkit/api/blade_chassis.py
oneview_redfish_toolkit/api/capabilities_object.py
oneview_redfish_toolkit/api/chassis.py
oneview_redfish_toolkit/api/chassis_collection.py
oneview_redfish_toolkit/api/composition_service.py
oneview_redfish_toolkit/api/computer_system.py
oneview_redfish_toolkit/api/computer_system_collection.py
oneview_redfish_toolkit/api/drive.py
oneview_redfish_toolkit/api/enclosure_chassis.py
oneview_redfish_toolkit/api/errors.py
oneview_redfish_toolkit/api/ethernet_interface.py
oneview_redfish_toolkit/api/ethernet_interface_collection.py
oneview_redfish_toolkit/api/event.py
oneview_redfish_toolkit/api/event_service.py
oneview_redfish_toolkit/api/manager.py
oneview_redfish_toolkit/api/manager_collection.py
oneview_redfish_toolkit/api/metadata.py
oneview_redfish_toolkit/api/network_adapter.py
oneview_redfish_toolkit/api/network_adapter_collection.py
oneview_redfish_toolkit/api/network_device_function.py
oneview_redfish_toolkit/api/network_device_function_collection.py
oneview_redfish_toolkit/api/network_interface.py
oneview_redfish_toolkit/api/network_interface_collection.py
oneview_redfish_toolkit/api/network_port.py
