Metadata-Version: 2.1
Name: oneview-redfish-toolkit
Version: 0.3.3
Summary: 'This toolkit provides a REST service to answer DMTF\'s Redfish compliant requests by querying HPE OneView.'
Home-page: https://github.com/HewlettPackard/oneview-redfish-toolkit
Author: Hewlett Packard Enterprise Development LP
Author-email: oneview-redfish-toolkit@hpe.com
License: 'Apache License 2.0'
Download-URL: https://github.com/HewlettPackard/oneview-redfish-toolkit/tarball/0.3.3
Platform: UNKNOWN
Classifier: Environment :: Web Environment
Classifier: Intended Audience :: Information Technology
Classifier: Intended Audience :: System Administrators
Classifier: License :: OSI Approved :: Apache Software License
Classifier: Operating System :: POSIX :: Linux
Classifier: Programming Language :: Python
Classifier: Programming Language :: Python :: 2
Classifier: Programming Language :: Python :: 2.7
Classifier: Programming Language :: Python :: 3
Classifier: Programming Language :: Python :: 3.3
Classifier: Programming Language :: Python :: 3.4
Classifier: Programming Language :: Python :: 3.5
Requires-Python: >=3.5
